tun_justice/__init__.py
tun_justice/courts.py
tun_justice/searcher.py
tun_justice-0.2.0.dist-info/LICENSE
tun_justice-0.2.0.dist-info/METADATA
tun_justice-0.2.0.dist-info/WHEEL
tun_justice-0.2.0.dist-info/top_level.txt
tun_justice-0.2.0.dist-info/RECORD
