Metadata-Version: 2.1
Name: tun_justice
Version: 0.2.0
Summary: A library for searching Tunisian court cases from the public judicial repository e-justice.tn.
Home-page: https://github.com/MedAouadhi/tun_justice
Author: Mohamed Aouadhi
Author-email: med.aouadhi@tutamail.com
Classifier: Programming Language :: Python :: 3
Classifier: License :: OSI Approved :: MIT License
Classifier: Operating System :: OS Independent
Requires-Python: >=3.6
License-File: LICENSE
Requires-Dist: requests>=2.32.3
Requires-Dist: beautifulsoup4>=4.12.3
